[[[{"imdb": 5.7}, {"name": "Fantastic Four"}, {"genre": ["Action", "Adventure", "Family"]}]], [[{"imdb": 5.7}, {"name": "Transformers: Age of Extinction"}, {"genre": ["Action", "Adventure", "Sci-Fi"]}]], [[{"imdb": 5.8}, {"name": "2012"}, {"genre": ["Action", "Adventure", "Sci-Fi"]}]], [[{"imdb": 6.0}, {"name": "Transformers: Revenge of the Fallen"}, {"genre": ["Action", "Adventure", "Sci-Fi"]}]], [[{"imdb": 6.1}, {"name": "Suicide Squad"}, {"genre": ["Action", "Adventure", "Fantasy"]}]], [[{"imdb": 6.1}, {"name": "Men in Black II"}, {"genre": ["Action", "Adventure", "Comedy"]}]], [[{"imdb": 6.2}, {"name": "Spider-Man 3"}, {"genre": ["Action", "Adventure", "Sci-Fi"]}]], [[{"imdb": 6.2}, {"name": "Indiana Jones and the Kingdom of the Crystal Skull"}, {"genre": ["Action", "Adventure", "Fantasy"]}]], [[{"imdb": 6.3}, {"name": "Transformers: Dark of the Moon"}, {"genre": ["Action", "Adventure", "Sci-Fi"]}]], [[{"imdb": 6.3}, {"name": "The Mummy Returns"}, {"genre": ["Action", "Adventure", "Fantasy"]}]], [[{"imdb": 6.4}, {"name": "The Day After Tomorrow"}, {"genre": ["Action", "Adventure", "Sci-Fi"]}]], [[{"imdb": 6.4}, {"name": "Godzilla"}, {"genre": ["Action", "Adventure", "Sci-Fi"]}]], [[{"imdb": 6.5}, {"name": "Star Wars: Episode I - The Phantom Menace"}, {"genre": ["Action", "Adventure", "Fantasy"]}]], [[{"imdb": 6.5}, {"name": "War of the Worlds"}, {"genre": ["Adventure", "Sci-Fi", "Thriller"]}]], [[{"imdb": 6.5}, {"name": "Alice in Wonderland"}, {"genre": ["Adventure", "Family", "Fantasy"]}]], [[{"imdb": 6.5}, {"name": "The Lost World: Jurassic Park"}, {"genre": ["Action", "Adventure", "Sci-Fi"]}]], [[{"imdb": 6.5}, {"name": "The Expendables"}, {"genre": ["Action", "Adventure", "Thriller"]}]], [[{"imdb": 6.6}, {"name": "Star Wars: Episode II - Attack of the Clones"}, {"genre": ["Action", "Adventure", "Fantasy"]}]], [[{"imdb": 6.6}, {"name": "Batman v Superman: Dawn of Justice"}, {"genre": ["Action", "Adventure", "Fantasy"]}]], [[{"imdb": 6.6}, {"name": "Pirates of the Caribbean: On Stranger Tides"}, {"genre": ["Action", "Adventure", "Fantasy"]}]], [[{"imdb": 6.6}, {"name": "X-Men Origins: Wolverine"}, {"genre": ["Action", "Adventure", "Sci-Fi"]}]], [[{"imdb": 6.6}, {"name": "Quantum of Solace"}, {"genre": ["Action", "Adventure", "Thriller"]}]], [[{"imdb": 6.6}, {"name": "Armageddon"}, {"genre": ["Action", "Adventure", "Sci-Fi"]}]], [[{"imdb": 6.6}, {"name": "Terminator Salvation"}, {"genre": ["Action", "Adventure", "Sci-Fi"]}]], [[{"imdb": 6.7}, {"name": "X-Men: O Confronto Final"}, {"genre": ["Action", "Adventure", "Fantasy"]}]], [[{"imdb": 6.7}, {"name": "Divergent"}, {"genre": ["Adventure", "Mystery", "Sci-Fi"]}]], [[{"imdb": 6.7}, {"name": "The Wolverine"}, {"genre": ["Action", "Adventure", "Sci-Fi"]}]], [[{"imdb": 6.7}, {"name": "The Amazing Spider-Man 2"}, {"genre": ["Action", "Adventure", "Sci-Fi"]}]], [[{"imdb": 6.7}, {"name": "Charlie and the Chocolate Factory"}, {"genre": ["Adventure", "Comedy", "Family"]}]], [[{"imdb": 6.7}, {"name": "The Hunger Games: Mockingjay - Part 1"}, {"genre": ["Action", "Adventure", "Sci-Fi"]}]], [[{"imdb": 6.8}, {"name": "The Incredible Hulk"}, {"genre": ["Action", "Adventure", "Sci-Fi"]}]], [[{"imdb": 6.8}, {"name": "Spectre"}, {"genre": ["Action", "Adventure", "Thriller"]}]], [[{"imdb": 6.8}, {"name": "Men in Black 3"}, {"genre": ["Action", "Adventure", "Comedy"]}]], [[{"imdb": 6.8}, {"name": "TRON: Legacy"}, {"genre": ["Action", "Adventure", "Sci-Fi"]}]], [[{"imdb": 6.9}, {"name": "Captain America: The First Avenger"}, {"genre": ["Action", "Adventure", "Sci-Fi"]}]], [[{"imdb": 6.9}, {"name": "Pacific Rim"}, {"genre": ["Action", "Adventure", "Sci-Fi"]}]], [[{"imdb": 6.9}, {"name": "The Chronicles of Narnia: The Lion, the Witch and the Wardrobe"}, {"genre": ["Adventure", "Family", "Fantasy"]}]], [[{"imdb": 6.9}, {"name": "Madagascar"}, {"genre": ["Animation", "Adventure", "Comedy"]}]], [[{"imdb": 6.9}, {"name": "Mission: Impossible III"}, {"genre": ["Action", "Adventure", "Thriller"]}]], [[{"imdb": 6.9}, {"name": "The Island"}, {"genre": ["Action", "Adventure", "Romance"]}]], [[{"imdb": 6.9}, {"name": "National Treasure"}, {"genre": ["Action", "Adventure", "Family"]}]], [[{"imdb": 7.0}, {"name": "Thor"}, {"genre": ["Action", "Adventure", "Fantasy"]}]], [[{"imdb": 7.0}, {"name": "Iron Man 2"}, {"genre": ["Action", "Adventure", "Sci-Fi"]}]], [[{"imdb": 7.0}, {"name": "World War Z"}, {"genre": ["Action", "Adventure", "Horror"]}]], [[{"imdb": 7.0}, {"name": "Prometheus"}, {"genre": ["Adventure", "Mystery", "Sci-Fi"]}]], [[{"imdb": 7.0}, {"name": "The Amazing Spider-Man"}, {"genre": ["Action", "Adventure", "Sci-Fi"]}]], [[{"imdb": 7.0}, {"name": "Jurassic World"}, {"genre": ["Action", "Adventure", "Sci-Fi"]}]], [[{"imdb": 7.0}, {"name": "Thor: The Dark World"}, {"genre": ["Action", "Adventure", "Sci-Fi"]}]], [[{"imdb": 7.0}, {"name": "Independence Day"}, {"genre": ["Action", "Adventure", "Sci-Fi"]}]], [[{"imdb": 7.0}, {"name": "Oblivion"}, {"genre": ["Action", "Adventure", "Mystery"]}]], [[{"imdb": 7.0}, {"name": "The Mummy"}, {"genre": ["Action", "Adventure", "Fantasy"]}]], [[{"imdb": 7.0}, {"name": "X-Men: Apocalypse"}, {"genre": ["Action", "Adventure", "Sci-Fi"]}]], [[{"imdb": 7.0}, {"name": "Maleficent"}, {"genre": ["Action", "Adventure", "Family"]}]], [[{"imdb": 7.1}, {"name": "Man of Steel"}, {"genre": ["Action", "Adventure", "Fantasy"]}]], [[{"imdb": 7.1}, {"name": "Transformers"}, {"genre": ["Action", "Adventure", "Sci-Fi"]}]], [[{"imdb": 7.1}, {"name": "Pirates of the Caribbean: At World's End"}, {"genre": ["Action", "Adventure", "Fantasy"]}]], [[{"imdb": 7.1}, {"name": "I, Robot"}, {"genre": ["Action", "Adventure", "Crime"]}]], [[{"imdb": 7.1}, {"name": "Mission: Impossible"}, {"genre": ["Action", "Adventure", "Thriller"]}]], [[{"imdb": 7.1}, {"name": "Brave"}, {"genre": ["Animation", "Adventure", "Comedy"]}]], [[{"imdb": 7.2}, {"name": "The Hunger Games"}, {"genre": ["Adventure", "Sci-Fi", "Thriller"]}]], [[{"imdb": 7.2}, {"name": "Iron Man 3"}, {"genre": ["Action", "Adventure", "Sci-Fi"]}]], [[{"imdb": 7.2}, {"name": "Live Free or Die Hard"}, {"genre": ["Action", "Adventure", "Thriller"]}]], [[{"imdb": 7.2}, {"name": "Shrek 2"}, {"genre": ["Animation", "Adventure", "Comedy"]}]], [[{"imdb": 7.2}, {"name": "King Kong"}, {"genre": ["Action", "Adventure", "Drama"]}]], [[{"imdb": 7.2}, {"name": "Speed"}, {"genre": ["Action", "Adventure", "Crime"]}]], [[{"imdb": 7.3}, {"name": "Spider-Man"}, {"genre": ["Action", "Adventure", "Sci-Fi"]}]], [[{"imdb": 7.3}, {"name": "Pirates of the Caribbean: Dead Man's Chest"}, {"genre": ["Action", "Adventure", "Fantasy"]}]], [[{"imdb": 7.3}, {"name": "Spider-Man 2"}, {"genre": ["Action", "Adventure", "Sci-Fi"]}]], [[{"imdb": 7.3}, {"name": "Men in Black"}, {"genre": ["Adventure", "Comedy", "Family"]}]], [[{"imdb": 7.3}, {"name": "Ant-Man"}, {"genre": ["Action", "Adventure", "Comedy"]}]], [[{"imdb": 7.3}, {"name": "Star Wars: The Last Jedi"}, {"genre": ["Action", "Adventure", "Fantasy"]}]], [[{"imdb": 7.3}, {"name": "Monsters University"}, {"genre": ["Animation", "Adventure", "Comedy"]}]], [[{"imdb": 7.4}, {"name": "Avengers: Age of Ultron"}, {"genre": ["Action", "Adventure", "Sci-Fi"]}]], [[{"imdb": 7.4}, {"name": "X-Men"}, {"genre": ["Action", "Adventure", "Sci-Fi"]}]], [[{"imdb": 7.4}, {"name": "Harry Potter and the Chamber of Secrets"}, {"genre": ["Adventure", "Family", "Fantasy"]}]], [[{"imdb": 7.4}, {"name": "The Hobbit: The Battle of the Five Armies"}, {"genre": ["Adventure", "Fantasy"]}]], [[{"imdb": 7.4}, {"name": "Mission: Impossible - Ghost Protocol"}, {"genre": ["Action", "Adventure", "Thriller"]}]], [[{"imdb": 7.4}, {"name": "Back to the Future Part III"}, {"genre": ["Adventure", "Comedy", "Sci-Fi"]}]], [[{"imdb": 7.4}, {"name": "Despicable Me 2"}, {"genre": ["Animation", "Adventure", "Comedy"]}]], [[{"imdb": 7.4}, {"name": "Fantastic Beasts and Where to Find Them"}, {"genre": ["Adventure", "Family", "Fantasy"]}]], [[{"imdb": 7.4}, {"name": "The Rock"}, {"genre": ["Action", "Adventure", "Thriller"]}]], [[{"imdb": 7.4}, {"name": "The Simpsons Movie"}, {"genre": ["Animation", "Adventure", "Comedy"]}]], [[{"imdb": 7.4}, {"name": "Miss\u00e3o: Imposs\u00edvel - Na\u00e7\u00e3o Secreta"}, {"genre": ["Action", "Adventure", "Thriller"]}]], [[{"imdb": 7.5}, {"name": "The Hunger Games: Catching Fire"}, {"genre": ["Action", "Adventure", "Mystery"]}]], [[{"imdb": 7.5}, {"name": "Frozen"}, {"genre": ["Animation", "Adventure", "Comedy"]}]], [[{"imdb": 7.5}, {"name": "X-Men 2"}, {"genre": ["Action", "Adventure", "Fantasy"]}]], [[{"imdb": 7.5}, {"name": "Doctor Strange"}, {"genre": ["Action", "Adventure", "Fantasy"]}]], [[{"imdb": 7.5}, {"name": "Harry Potter and the Order of the Phoenix"}, {"genre": ["Adventure", "Family", "Fantasy"]}]], [[{"imdb": 7.5}, {"name": "Wonder Woman"}, {"genre": ["Action", "Adventure", "Fantasy"]}]], [[{"imdb": 7.5}, {"name": "Sherlock Holmes: A Game of Shadows"}, {"genre": ["Action", "Adventure", "Crime"]}]], [[{"imdb": 7.5}, {"name": "Ice Age"}, {"genre": ["Animation", "Adventure", "Comedy"]}]], [[{"imdb": 7.5}, {"name": "Spider-Man: Homecoming"}, {"genre": ["Action", "Adventure", "Sci-Fi"]}]], [[{"imdb": 7.5}, {"name": "Black Panther"}, {"genre": ["Action", "Adventure", "Sci-Fi"]}]], [[{"imdb": 7.5}, {"name": "Hugo"}, {"genre": ["Adventure", "Drama", "Family"]}]], [[{"imdb": 7.6}, {"name": "Star Wars: Episode III - Revenge of the Sith"}, {"genre": ["Action", "Adventure", "Fantasy"]}]], [[{"imdb": 7.6}, {"name": "Sherlock Holmes"}, {"genre": ["Action", "Adventure", "Crime"]}]], [[{"imdb": 7.6}, {"name": "Harry Potter and the Sorcerer's Stone"}, {"genre": ["Adventure", "Family", "Fantasy"]}]], [[{"imdb": 7.6}, {"name": "Harry Potter and the Half-Blood Prince"}, {"genre": ["Adventure", "Family", "Fantasy"]}]], [[{"imdb": 7.6}, {"name": "Indiana Jones and the Temple of Doom"}, {"genre": ["Action", "Adventure"]}]], [[{"imdb": 7.6}, {"name": "Dawn of the Planet of the Apes"}, {"genre": ["Action", "Adventure", "Drama"]}]], [[{"imdb": 7.6}, {"name": "Kung Fu Panda"}, {"genre": ["Animation", "Action", "Adventure"]}]], [[{"imdb": 7.6}, {"name": "Die Hard with a Vengeance"}, {"genre": ["Action", "Adventure", "Thriller"]}]], [[{"imdb": 7.6}, {"name": "127 Hours"}, {"genre": ["Adventure", "Biography", "Drama"]}]], [[{"imdb": 7.6}, {"name": "Batman"}, {"genre": ["Action", "Adventure"]}]], [[{"imdb": 7.7}, {"name": "Kingsman: The Secret Service"}, {"genre": ["Action", "Adventure", "Comedy"]}]], [[{"imdb": 7.7}, {"name": "Harry Potter and the Goblet of Fire"}, {"genre": ["Adventure", "Family", "Fantasy"]}]], [[{"imdb": 7.7}, {"name": "Minority Report"}, {"genre": ["Action", "Adventure", "Crime"]}]], [[{"imdb": 7.7}, {"name": "Despicable Me"}, {"genre": ["Animation", "Adventure", "Comedy"]}]], [[{"imdb": 7.7}, {"name": "Zombieland"}, {"genre": ["Adventure", "Comedy", "Horror"]}]], [[{"imdb": 7.7}, {"name": "Star Trek: Into Darkness"}, {"genre": ["Action", "Adventure", "Sci-Fi"]}]], [[{"imdb": 7.7}, {"name": "Harry Potter and the Deathly Hallows: Part 1"}, {"genre": ["Adventure", "Family", "Fantasy"]}]], [[{"imdb": 7.7}, {"name": "The Fifth Element"}, {"genre": ["Action", "Adventure", "Sci-Fi"]}]], [[{"imdb": 7.7}, {"name": "Guardians of the Galaxy Vol. 2"}, {"genre": ["Action", "Adventure", "Sci-Fi"]}]], [[{"imdb": 7.7}, {"name": "Arrow"}, {"genre": ["Action", "Adventure", "Crime"]}]], [[{"imdb": 7.7}, {"name": "Wreck-It Ralph"}, {"genre": ["Animation", "Adventure", "Comedy"]}]], [[{"imdb": 7.8}, {"name": "Avatar"}, {"genre": ["Action", "Adventure", "Fantasy"]}]], [[{"imdb": 7.8}, {"name": "Captain America: The Winter Soldier"}, {"genre": ["Action", "Adventure", "Sci-Fi"]}]], [[{"imdb": 7.8}, {"name": "X-Men: First Class"}, {"genre": ["Action", "Adventure", "Sci-Fi"]}]], [[{"imdb": 7.8}, {"name": "Skyfall"}, {"genre": ["Action", "Adventure", "Thriller"]}]], [[{"imdb": 7.8}, {"name": "Captain America: Civil War"}, {"genre": ["Action", "Adventure", "Sci-Fi"]}]], [[{"imdb": 7.8}, {"name": "Harry Potter and the Prisoner of Azkaban"}, {"genre": ["Adventure", "Family", "Fantasy"]}]], [[{"imdb": 7.8}, {"name": "Cast Away"}, {"genre": ["Adventure", "Drama", "Romance"]}]], [[{"imdb": 7.8}, {"name": "Rogue One: A Star Wars Story"}, {"genre": ["Action", "Adventure", "Sci-Fi"]}]], [[{"imdb": 7.8}, {"name": "Back to the Future Part II"}, {"genre": ["Adventure", "Comedy", "Sci-Fi"]}]], [[{"imdb": 7.8}, {"name": "Tangled"}, {"genre": ["Animation", "Adventure", "Comedy"]}]], [[{"imdb": 7.8}, {"name": "Big Hero 6"}, {"genre": ["Animation", "Action", "Adventure"]}]], [[{"imdb": 7.8}, {"name": "The Lego Movie"}, {"genre": ["Animation", "Action", "Adventure"]}]], [[{"imdb": 7.8}, {"name": "Moonrise Kingdom"}, {"genre": ["Adventure", "Comedy", "Drama"]}]], [[{"imdb": 7.9}, {"name": "Iron Man"}, {"genre": ["Action", "Adventure", "Sci-Fi"]}]], [[{"imdb": 7.9}, {"name": "The Hobbit: An Unexpected Journey"}, {"genre": ["Adventure", "Family", "Fantasy"]}]], [[{"imdb": 7.9}, {"name": "The Hobbit: The Desolation of Smaug"}, {"genre": ["Adventure", "Fantasy"]}]], [[{"imdb": 7.9}, {"name": "Shrek"}, {"genre": ["Animation", "Adventure", "Comedy"]}]], [[{"imdb": 7.9}, {"name": "Edge of Tomorrow"}, {"genre": ["Action", "Adventure", "Sci-Fi"]}]], [[{"imdb": 7.9}, {"name": "Life of Pi"}, {"genre": ["Adventure", "Drama", "Fantasy"]}]], [[{"imdb": 7.9}, {"name": "Toy Story 2"}, {"genre": ["Animation", "Adventure", "Comedy"]}]], [[{"imdb": 7.9}, {"name": "Thor: Ragnarok"}, {"genre": ["Action", "Adventure", "Comedy"]}]], [[{"imdb": 8.0}, {"name": "Pirates of the Caribbean: The Curse of the Black Pearl"}, {"genre": ["Action", "Adventure", "Fantasy"]}]], [[{"imdb": 8.0}, {"name": "Star Wars: The Force Awakens"}, {"genre": ["Action", "Adventure", "Fantasy"]}]], [[{"imdb": 8.0}, {"name": "Deadpool"}, {"genre": ["Action", "Adventure", "Comedy"]}]], [[{"imdb": 8.0}, {"name": "The Martian"}, {"genre": ["Adventure", "Drama", "Sci-Fi"]}]], [[{"imdb": 8.0}, {"name": "X-Men: Days of Future Past"}, {"genre": ["Action", "Adventure", "Sci-Fi"]}]], [[{"imdb": 8.0}, {"name": "The Revenant"}, {"genre": ["Adventure", "Drama", "History"]}]], [[{"imdb": 8.0}, {"name": "The Incredibles"}, {"genre": ["Animation", "Action", "Adventure"]}]], [[{"imdb": 8.0}, {"name": "Star Trek"}, {"genre": ["Action", "Adventure", "Sci-Fi"]}]], [[{"imdb": 8.0}, {"name": "Ratatouille"}, {"genre": ["Animation", "Adventure", "Comedy"]}]], [[{"imdb": 8.0}, {"name": "Casino Royale"}, {"genre": ["Action", "Adventure", "Thriller"]}]], [[{"imdb": 8.0}, {"name": "Jaws"}, {"genre": ["Adventure", "Drama", "Thriller"]}]], [[{"imdb": 8.0}, {"name": "Diamante de Sangue"}, {"genre": ["Adventure", "Drama", "Thriller"]}]], [[{"imdb": 8.0}, {"name": "Big Fish"}, {"genre": ["Adventure", "Drama", "Fantasy"]}]], [[{"imdb": 8.0}, {"name": "Zootopia"}, {"genre": ["Animation", "Adventure", "Comedy"]}]], [[{"imdb": 8.0}, {"name": "The Wizard of Oz"}, {"genre": ["Adventure", "Family", "Fantasy"]}]], [[{"imdb": 8.0}, {"name": "Aladdin"}, {"genre": ["Animation", "Adventure", "Comedy"]}]], [[{"imdb": 8.1}, {"name": "The Avengers"}, {"genre": ["Action", "Adventure", "Sci-Fi"]}]], [[{"imdb": 8.1}, {"name": "Guardians of the Galaxy"}, {"genre": ["Action", "Adventure", "Sci-Fi"]}]], [[{"imdb": 8.1}, {"name": "Finding Nemo"}, {"genre": ["Animation", "Adventure", "Comedy"]}]], [[{"imdb": 8.1}, {"name": "Jurassic Park"}, {"genre": ["Adventure", "Sci-Fi", "Thriller"]}]], [[{"imdb": 8.1}, {"name": "Mad Max: Fury Road"}, {"genre": ["Action", "Adventure", "Sci-Fi"]}]], [[{"imdb": 8.1}, {"name": "Monsters, Inc."}, {"genre": ["Animation", "Adventure", "Comedy"]}]], [[{"imdb": 8.1}, {"name": "Harry Potter and the Deathly Hallows: Part 2"}, {"genre": ["Adventure", "Drama", "Fantasy"]}]], [[{"imdb": 8.1}, {"name": "The Grand Budapest Hotel"}, {"genre": ["Adventure", "Comedy", "Drama"]}]], [[{"imdb": 8.1}, {"name": "How to Train Your Dragon"}, {"genre": ["Animation", "Action", "Adventure"]}]], [[{"imdb": 8.1}, {"name": "Into the Wild"}, {"genre": ["Adventure", "Biography", "Drama"]}]], [[{"imdb": 8.1}, {"name": "The Princess Bride"}, {"genre": ["Adventure", "Family", "Fantasy"]}]], [[{"imdb": 8.1}, {"name": "Stand by Me"}, {"genre": ["Adventure", "Drama"]}]], [[{"imdb": 8.2}, {"name": "Inside Out"}, {"genre": ["Animation", "Adventure", "Comedy"]}]], [[{"imdb": 8.3}, {"name": "Batman Begins"}, {"genre": ["Action", "Adventure"]}]], [[{"imdb": 8.3}, {"name": "Bastardos Ingl\u00f3rios"}, {"genre": ["Adventure", "Drama", "War"]}]], [[{"imdb": 8.3}, {"name": "Star Wars: Episode VI - Return of the Jedi"}, {"genre": ["Action", "Adventure", "Fantasy"]}]], [[{"imdb": 8.3}, {"name": "Up"}, {"genre": ["Animation", "Adventure", "Comedy"]}]], [[{"imdb": 8.3}, {"name": "Toy Story"}, {"genre": ["Animation", "Adventure", "Comedy"]}]], [[{"imdb": 8.3}, {"name": "Toy Story 3"}, {"genre": ["Animation", "Adventure", "Comedy"]}]], [[{"imdb": 8.3}, {"name": "Indiana Jones and the Last Crusade"}, {"genre": ["Action", "Adventure", "Fantasy"]}]], [[{"imdb": 8.3}, {"name": "2001: A Space Odyssey"}, {"genre": ["Adventure", "Sci-Fi"]}]], [[{"imdb": 8.3}, {"name": "Monty Python and the Holy Grail"}, {"genre": ["Adventure", "Comedy", "Fantasy"]}]], [[{"imdb": 8.4}, {"name": "WALL\u00b7E"}, {"genre": ["Animation", "Adventure", "Family"]}]], [[{"imdb": 8.4}, {"name": "Aliens"}, {"genre": ["Action", "Adventure", "Sci-Fi"]}]], [[{"imdb": 8.4}, {"name": "Lost"}, {"genre": ["Adventure", "Drama", "Fantasy"]}]], [[{"imdb": 8.4}, {"name": "Princess Mononoke"}, {"genre": ["Animation", "Adventure", "Fantasy"]}]], [[{"imdb": 8.5}, {"name": "Gladiator"}, {"genre": ["Action", "Adventure", "Drama"]}]], [[{"imdb": 8.5}, {"name": "Back to the Future"}, {"genre": ["Adventure", "Comedy", "Sci-Fi"]}]], [[{"imdb": 8.5}, {"name": "The Lion King"}, {"genre": ["Animation", "Adventure", "Drama"]}]], [[{"imdb": 8.5}, {"name": "Raiders of the Lost Ark"}, {"genre": ["Action", "Adventure"]}]], [[{"imdb": 8.6}, {"name": "Interstellar"}, {"genre": ["Adventure", "Drama", "Sci-Fi"]}]], [[{"imdb": 8.6}, {"name": "Star Wars: Episode IV - A New Hope"}, {"genre": ["Action", "Adventure", "Fantasy"]}]], [[{"imdb": 8.6}, {"name": "Spirited Away"}, {"genre": ["Animation", "Adventure", "Family"]}]], [[{"imdb": 8.6}, {"name": "Vikings"}, {"genre": ["Action", "Adventure", "Drama"]}]], [[{"imdb": 8.7}, {"name": "The Lord of the Rings: The Two Towers"}, {"genre": ["Adventure", "Drama", "Fantasy"]}]], [[{"imdb": 8.8}, {"name": "Inception"}, {"genre": ["Action", "Adventure", "Sci-Fi"]}]], [[{"imdb": 8.8}, {"name": "The Lord of the Rings: The Fellowship of the Ring"}, {"genre": ["Adventure", "Drama", "Fantasy"]}]], [[{"imdb": 8.8}, {"name": "Star Wars: Episode V - The Empire Strikes Back"}, {"genre": ["Action", "Adventure", "Fantasy"]}]], [[{"imdb": 8.8}, {"name": "Avengers: Infinity War"}, {"genre": ["Action", "Adventure", "Fantasy"]}]], [[{"imdb": 8.9}, {"name": "The Lord of the Rings: The Return of the King"}, {"genre": ["Adventure", "Drama", "Fantasy"]}]], [[{"imdb": 9.5}, {"name": "Game of Thrones"}, {"genre": ["Action", "Adventure", "Drama"]}]]]